detect_llm_api_keys/__init__.py
detect_llm_api_keys/__main__.py
detect_llm_api_keys/api_key_regexes.py
detect_llm_api_keys/key_detector.py
detect_llm_api_keys-0.0.3.dist-info/LICENSE
detect_llm_api_keys-0.0.3.dist-info/METADATA
detect_llm_api_keys-0.0.3.dist-info/WHEEL
detect_llm_api_keys-0.0.3.dist-info/entry_points.txt
detect_llm_api_keys-0.0.3.dist-info/top_level.txt
detect_llm_api_keys-0.0.3.dist-info/RECORD
