Metadata-Version: 2.1
Name: detect-llm-api-keys
Version: 0.0.3
Summary: scan python files for llm api keys (designed for pre-commit)
Author: Joshua Sundance Bailey
License: MIT License
Project-URL: Homepage, https://github.com/joshuasundance-swca/detect_llm_api_keys
Keywords: llm,api,security,lint,pre-commit
Classifier: License :: OSI Approved :: MIT License
Classifier: Operating System :: OS Independent
Classifier: Programming Language :: Python
Classifier: Programming Language :: Python :: 3
Classifier: Programming Language :: Python :: 3.9
Requires-Python: >=3.9
License-File: LICENSE
Provides-Extra: dev
Requires-Dist: bumpver ; extra == 'dev'
Requires-Dist: coverage ; extra == 'dev'
Requires-Dist: coverage-badge ; extra == 'dev'
Requires-Dist: pre-commit ; extra == 'dev'
Requires-Dist: pytest ; extra == 'dev'
Provides-Extra: doc
Requires-Dist: sphinx ; extra == 'doc'
Requires-Dist: sphinx-rtd-theme ; extra == 'doc'
